{
  "project_info": {
    "project_number": "288761821690",
    "project_id": "task-beat",
    "storage_bucket": "task-beat.firebasestorage.app"
  },
  "client": [
    {
      "client_info": {
        "mobilesdk_app_id": "1:288761821690:android:a0afe2f1fc748d9c0a0c43",
        "android_client_info": {
          "package_name": "com.example.taskbeat"
        }
      },
      "oauth_client": [
        {
          "client_id": "288761821690-j5e1ctab6jgelgssusog27bderi625un.apps.googleusercontent.com",
          "client_type": 1,
          "android_info": {
            "package_name": "com.example.taskbeat",
            "certificate_hash": "30e9e72efb99038672976432b283afa864e42418"
          }
        },
        {
          "client_id": "288761821690-0uc9vqjr0pr3j601mqln3ku4slmoh96d.apps.googleusercontent.com",
          "client_type": 3
        }
      ],
      "api_key": [
        {
          "current_key": "AIzaSyBHxcG1gWNRJzkKQxg5B35eSoYJUFcwmzs"
        }
      ],
      "services": {
        "appinvite_service": {
          "other_platform_oauth_client": [
            {
              "client_id": "288761821690-0uc9vqjr0pr3j601mqln3ku4slmoh96d.apps.googleusercontent.com",
              "client_type": 3
            }
          ]
        }
      }
    }
  ],
  "configuration_version": "1"
}